Metadata-Version: 2.1
Name: MxbaiduAi
Version: 0.0.4
Summary: UNKNOWN
Home-page: https://github.com/yuanyunqiang/
Author: YuanYunQiang
Author-email: 649756903@qq.com
License: MIT Licence
Keywords: pip,SICA,featureextraction
Platform: any
